emqx_client_monitor/__about__.py
emqx_client_monitor/__init__.py
emqx_client_monitor/__main__.py
emqx_client_monitor/cli/__init__.py
emqx_client_monitor/cli/table.py
emqx_client_monitor/config/load.py
emqx_client_monitor/config/schema.py
emqx_client_monitor/emqx/api.py
emqx_client_monitor/emqx/client_info.py
emqx_client_monitor/prom/exporter.py
emqx_client_monitor-0.3.1.dist-info/METADATA
emqx_client_monitor-0.3.1.dist-info/WHEEL
emqx_client_monitor-0.3.1.dist-info/entry_points.txt
emqx_client_monitor-0.3.1.dist-info/licenses/LICENSE
emqx_client_monitor-0.3.1.dist-info/RECORD
