Metadata-Version: 2.4
Name: emqx-client-monitor
Version: 0.3.1
Summary: Prometheus-compatible exporter/monitor for watching EMQX MQTT clients.
Project-URL: Documentation, https://github.com/danielskowronski/emqx-client-monitor
Project-URL: Issues, https://github.com/danielskowronski/emqx-client-monitor/issues
Project-URL: Source, https://github.com/danielskowronski/emqx-client-monitor
Author-email: Daniel Skowroński <daniel@skowron.ski>
License-Expression: BSD-3-Clause
License-File: LICENSE
Keywords: emqx,exporter,iot,monitoring,mqtt,prometheus
Classifier: Development Status :: 4 - Beta
Classifier: Programming Language :: Python
Classifier: Programming Language :: Python :: 3.11
Classifier: Programming Language :: Python :: 3.12
Classifier: Programming Language :: Python :: 3.13
Classifier: Programming Language :: Python :: 3.14
Classifier: Programming Language :: Python :: Implementation :: CPython
Classifier: Programming Language :: Python :: Implementation :: PyPy
Requires-Python: >=3.11
Requires-Dist: click~=8.3.1
Requires-Dist: human-readable~=2.0.0
Requires-Dist: prometheus-client~=0.22.1
Requires-Dist: pydantic~=2.12.5
Requires-Dist: pyyaml~=6.0.3
Requires-Dist: requests~=2.32.5
Requires-Dist: rich~=14.2.0
